<?xml version="1.0" encoding="UTF-8"?>
<!DOCTYPE suite SYSTEM "https://testng.org/testng-1.0.dtd">
<suite name="Suite2"  paralell = "tests" thread-count = "2">

  <test  name="Test1">
  <parameter name = "browsername" value = "chrome"></parameter>
    <classes>
      <class name="SeleniumTestCases.multiplebrowser"/>
    </classes> 
  </test> 
  
    <test  name="Test2">
  <parameter name = "browsername" value = "Firefox"></parameter>
    <classes>
      <class name="SeleniumTestCases.multiplebrowser"/>
    </classes>
  </test>   
</suite> 
